rst2ctags.py
rst2ctags-0.2.6.dist-info/LICENSE.txt
rst2ctags-0.2.6.dist-info/METADATA
rst2ctags-0.2.6.dist-info/WHEEL
rst2ctags-0.2.6.dist-info/entry_points.txt
rst2ctags-0.2.6.dist-info/top_level.txt
rst2ctags-0.2.6.dist-info/zip-safe
rst2ctags-0.2.6.dist-info/RECORD
