Metadata-Version: 2.1
Name: rst2ctags
Version: 0.2.6
Summary: Generates ctags-compatible output for the sections of a reStructuredText document.
Home-page: https://github.com/jszakmeister/rst2ctags
Author: John Szakmeister
Author-email: john@szakmeister.net
License: BSD
Platform: UNKNOWN
Classifier: License :: OSI Approved :: BSD License
Classifier: Development Status :: 5 - Production/Stable
Classifier: Environment :: Console
Classifier: Operating System :: OS Independent
Classifier: Programming Language :: Python :: 2.7
Classifier: Programming Language :: Python :: 3
Classifier: Topic :: Software Development
Classifier: Topic :: Text Processing
Classifier: Topic :: Text Processing :: Indexing
Classifier: Topic :: Utilities
